src/__init__.py
src/main.py
tests/__init__.py
tests/test_main.py
PyBlueprintMaker-0.1.2.dist-info/LICENSE
PyBlueprintMaker-0.1.2.dist-info/METADATA
PyBlueprintMaker-0.1.2.dist-info/WHEEL
PyBlueprintMaker-0.1.2.dist-info/entry_points.txt
PyBlueprintMaker-0.1.2.dist-info/top_level.txt
PyBlueprintMaker-0.1.2.dist-info/RECORD
