Metadata-Version: 2.1
Name: PyBlueprintMaker
Version: 0.1.2
Summary: Python-based tool that helps you create organized project directories or structures. It uses best practices and incorporates fixtures, pytest, and the Python Standard Library to ensure the quality of the project's organization and structure
Home-page: https://github.com/patimejia/PyBlueprintMaker
Author: Patricia Mejia
Author-email: contact@patimejia.com
Keywords: project-scaffolding project-structure python-project-template python-project-generator best-practices pytest fixtures python-standard-library code-quality project-management
Classifier: Development Status :: 3 - Alpha
Classifier: Intended Audience :: Developers
Classifier: License :: OSI Approved :: MIT License
Classifier: Programming Language :: Python :: 3
Classifier: Programming Language :: Python :: 3.6
Classifier: Programming Language :: Python :: 3.7
Classifier: Programming Language :: Python :: 3.8
Classifier: Programming Language :: Python :: 3.9
Classifier: Topic :: Software Development :: Libraries :: Python Modules
Classifier: Topic :: Utilities
License-File: LICENSE
